hublot/__init__.py
hublot/client.py
hublot/compile.py
hublot/config.py
hublot/datastructures.py
hublot/decorator.py
hublot/logs.py
hublot/py.typed
hublot/version.py
hublot/cache/__init__.py
hublot/cache/binaryblob.py
hublot/cache/cache.py
hublot/cache/key.py
hublot/cache/storage.py
hublot/engines/__init__.py
hublot/engines/base.py
hublot/engines/curlcmd.py
hublot/engines/pool.py
hublot/engines/pycurl.py
hublot/engines/register.py
hublot/engines/requests.py
hublot-2.0.1.dist-info/METADATA
hublot-2.0.1.dist-info/WHEEL
hublot-2.0.1.dist-info/top_level.txt
hublot-2.0.1.dist-info/RECORD
